Metadata-Version: 2.4
Name: logbuch-cli
Version: 1.0.0
Summary: The Ultimate AI-Powered CLI Productivity Platform
Home-page: https://github.com/yourusername/logbuch
Author: Alexander Straub
Author-email: Logbuch Contributors <logbuch@example.com>
License: MIT
Project-URL: Homepage, https://github.com/yourusername/logbuch
Project-URL: Documentation, https://github.com/yourusername/logbuch/docs
Project-URL: Repository, https://github.com/yourusername/logbuch
Project-URL: Bug Tracker, https://github.com/yourusername/logbuch/issues
Project-URL: Changelog, https://github.com/yourusername/logbuch/blob/main/CHANGELOG.md
Keywords: productivity,cli,task-management,ai,gamification,terminal,productivity-tools,time-tracking,journal,mood-tracking,ascii-art,commuter,weather,coaching
Classifier: Development Status :: 5 - Production/Stable
Classifier: Intended Audience :: Developers
Classifier: Intended Audience :: End Users/Desktop
Classifier: License :: OSI Approved :: MIT License
Classifier: Operating System :: OS Independent
Classifier: Programming Language :: Python :: 3
Classifier: Programming Language :: Python :: 3.8
Classifier: Programming Language :: Python :: 3.9
Classifier: Programming Language :: Python :: 3.10
Classifier: Programming Language :: Python :: 3.11
Classifier: Programming Language :: Python :: 3.12
Classifier: Topic :: Office/Business
Classifier: Topic :: Utilities
Classifier: Environment :: Console
Requires-Python: >=3.8
License-File: LICENSE
Requires-Dist: click>=8.0.0
Requires-Dist: rich>=13.0.0
Requires-Dist: python-dateutil>=2.8.0
Requires-Dist: pydantic>=1.10.0
Provides-Extra: dev
Requires-Dist: pytest>=7.0.0; extra == "dev"
Requires-Dist: pytest-cov>=4.0.0; extra == "dev"
Requires-Dist: pytest-mock>=3.10.0; extra == "dev"
Requires-Dist: black>=22.0.0; extra == "dev"
Requires-Dist: isort>=5.10.0; extra == "dev"
Requires-Dist: flake8>=5.0.0; extra == "dev"
Requires-Dist: mypy>=0.991; extra == "dev"
Requires-Dist: pre-commit>=2.20.0; extra == "dev"
Provides-Extra: integrations
Requires-Dist: requests>=2.28.0; extra == "integrations"
Requires-Dist: aiohttp>=3.8.0; extra == "integrations"
Provides-Extra: ai
Requires-Dist: openai>=0.27.0; extra == "ai"
Requires-Dist: anthropic>=0.3.0; extra == "ai"
Provides-Extra: docs
Requires-Dist: mkdocs>=1.4.0; extra == "docs"
Requires-Dist: mkdocs-material>=8.5.0; extra == "docs"
Dynamic: author
Dynamic: home-page
Dynamic: license-file
Dynamic: requires-python
